angka/__init__.py
angka/_angka.pyd
angka/angka.py
angka/libatk-1.0-0.dll
angka/libbrotlicommon.dll
angka/libbrotlidec.dll
angka/libbz2-1.dll
angka/libcairo-2.dll
angka/libcairo-gobject-2.dll
angka/libdatrie-1.dll
angka/libepoxy-0.dll
angka/libexpat-1.dll
angka/libffi-7.dll
angka/libfontconfig-1.dll
angka/libfreetype-6.dll
angka/libfribidi-0.dll
angka/libgcc_s_seh-1.dll
angka/libgdk-3-0.dll
angka/libgdk_pixbuf-2.0-0.dll
angka/libgio-2.0-0.dll
angka/libglib-2.0-0.dll
angka/libgmodule-2.0-0.dll
angka/libgobject-2.0-0.dll
angka/libgraphite2.dll
angka/libgtk-3-0.dll
angka/libharfbuzz-0.dll
angka/libiconv-2.dll
angka/libintl-8.dll
angka/libpango-1.0-0.dll
angka/libpangocairo-1.0-0.dll
angka/libpangoft2-1.0-0.dll
angka/libpangowin32-1.0-0.dll
angka/libpcre-1.dll
angka/libpixman-1-0.dll
angka/libpng-config
angka/libpng16-16.dll
angka/libpng16-config
angka/libstdc++-6.dll
angka/libthai-0.dll
angka/libwinpthread-1.dll
angka/zlib1.dll
angka/include/angka.h
angka/include/angkavisual.h
angka/include/init.h
angka/include/matrix.h
angka/include/plot.h
angka/include/standard.h
angka/include/vector.h
angka/libs/libagv.a
angka/libs/libagx.a
angka-0.0.3.dist-info/LICENSE
angka-0.0.3.dist-info/METADATA
angka-0.0.3.dist-info/WHEEL
angka-0.0.3.dist-info/top_level.txt
angka-0.0.3.dist-info/RECORD
