Metadata-Version: 2.1
Name: angka
Version: 0.0.3
Summary: a library for data manipulation and visualization
Home-page: https://github.com/yudhastyawan/angka
Author: Yudha Styawan
Author-email: yudhastyawan@gmail.com
License: UNKNOWN
Project-URL: Bug Tracker, https://github.com/yudhastyawan/angka/issues
Project-URL: Documentation, http://angka.readthedocs.io
Platform: UNKNOWN
Classifier: Programming Language :: Python :: 3
Classifier: License :: OSI Approved :: MIT License
Classifier: Operating System :: Microsoft :: Windows
Requires-Python: >=3.7
License-File: LICENSE
Requires-Dist: numpy
